{
  "acid_fast_mycobacteria.png": {
    "eli5": "Ziehl\u2013Neelsen stain: slender red acid-fast bacilli on blue background.",
    "labels": [
      {
        "x": 0.42,
        "y": 0.14,
        "w": 0.22,
        "h": 0.1,
        "text": "Acid-fast bacilli"
      },
      {
        "x": 0.28,
        "y": 0.51,
        "w": 0.14,
        "h": 0.17,
        "text": "Counterstain background"
      }
    ],
    "occlude": [
      {
        "x": 0.12,
        "y": 0.36,
        "w": 0.19,
        "h": 0.18,
        "text": "Hide bacilli label"
      }
    ]
  },
  "adipose_tissue_he.png": {
    "eli5": "Adipocytes: signet-ring cells with peripheral nuclei; clear vacuoles on H&E.",
    "labels": [
      {
        "x": 0.19,
        "y": 0.6,
        "w": 0.11,
        "h": 0.15,
        "text": "Adipocytes"
      },
      {
        "x": 0.4,
        "y": 0.71,
        "w": 0.21,
        "h": 0.11,
        "text": "Peripheral nuclei"
      }
    ],
    "occlude": [
      {
        "x": 0.39,
        "y": 0.74,
        "w": 0.18,
        "h": 0.12,
        "text": "Hide label"
      }
    ]
  },
  "alcian_blue_pas_mucins.png": {
    "eli5": "Alcian blue/PAS: acid mucins stain blue, neutral mucins stain magenta.",
    "labels": [
      {
        "x": 0.47,
        "y": 0.41,
        "w": 0.12,
        "h": 0.09,
        "text": "Neutral mucin (PAS+)"
      },
      {
        "x": 0.61,
        "y": 0.18,
        "w": 0.17,
        "h": 0.16,
        "text": "Acid mucin (Alcian blue+)"
      }
    ],
    "occlude": [
      {
        "x": 0.69,
        "y": 0.45,
        "w": 0.13,
        "h": 0.08,
        "text": "Hide label"
      }
    ]
  },
  "anaplasia_vs_normal.png": {
    "eli5": "Anaplasia: pleomorphic cells, hyperchromasia, high N:C ratio; loss of differentiation.",
    "labels": [
      {
        "x": 0.22,
        "y": 0.63,
        "w": 0.16,
        "h": 0.13,
        "text": "Pleomorphism"
      },
      {
        "x": 0.13,
        "y": 0.64,
        "w": 0.11,
        "h": 0.1,
        "text": "High N:C ratio"
      }
    ],
    "occlude": [
      {
        "x": 0.51,
        "y": 0.46,
        "w": 0.21,
        "h": 0.12,
        "text": "Hide label"
      }
    ]
  },
  "cell_adaptations_atrophy_hyperplasia_metaplasia.png": {
    "eli5": "Cell adaptations across atrophy, hypertrophy, hyperplasia, metaplasia, dysplasia.",
    "labels": [
      {
        "x": 0.24,
        "y": 0.36,
        "w": 0.14,
        "h": 0.15,
        "text": "Hypertrophy/Hyperplasia"
      },
      {
        "x": 0.69,
        "y": 0.47,
        "w": 0.22,
        "h": 0.14,
        "text": "Metaplasia/Dysplasia"
      }
    ],
    "occlude": [
      {
        "x": 0.12,
        "y": 0.46,
        "w": 0.21,
        "h": 0.15,
        "text": "Hide label"
      }
    ]
  },
  "clinical_pathology_leukemia_cells.png": {
    "eli5": "Peripheral smear with blasts: high N:C ratio, nucleoli\u2014think acute leukemia.",
    "labels": [
      {
        "x": 0.54,
        "y": 0.26,
        "w": 0.21,
        "h": 0.15,
        "text": "Blasts"
      },
      {
        "x": 0.69,
        "y": 0.14,
        "w": 0.16,
        "h": 0.11,
        "text": "Prominent nucleoli"
      }
    ],
    "occlude": [
      {
        "x": 0.23,
        "y": 0.43,
        "w": 0.21,
        "h": 0.14,
        "text": "Hide label"
      }
    ]
  },
  "clinical_pathology_virus_structure.png": {
    "eli5": "Enveloped RNA virus schematic with spikes and nucleocapsid.",
    "labels": [
      {
        "x": 0.46,
        "y": 0.49,
        "w": 0.21,
        "h": 0.08,
        "text": "Envelope + spikes"
      },
      {
        "x": 0.1,
        "y": 0.6,
        "w": 0.13,
        "h": 0.18,
        "text": "Nucleocapsid"
      }
    ],
    "occlude": [
      {
        "x": 0.65,
        "y": 0.7,
        "w": 0.11,
        "h": 0.18,
        "text": "Hide label"
      }
    ]
  },
  "colon_adenoma_histology.png": {
    "eli5": "Colonic adenoma: dysplastic, crowded glands with loss of mucin and stratification.",
    "labels": [
      {
        "x": 0.24,
        "y": 0.29,
        "w": 0.21,
        "h": 0.1,
        "text": "Crowded glands"
      },
      {
        "x": 0.58,
        "y": 0.54,
        "w": 0.2,
        "h": 0.11,
        "text": "Loss of mucin"
      }
    ],
    "occlude": [
      {
        "x": 0.36,
        "y": 0.2,
        "w": 0.12,
        "h": 0.09,
        "text": "Hide label"
      }
    ]
  },
  "connective_tissue_cartilage.png": {
    "eli5": "Cartilage: chondrocytes in lacunae; matrix with collagen (and elastin in elastic cartilage).",
    "labels": [
      {
        "x": 0.38,
        "y": 0.24,
        "w": 0.22,
        "h": 0.13,
        "text": "Chondrocytes in lacunae"
      },
      {
        "x": 0.11,
        "y": 0.15,
        "w": 0.14,
        "h": 0.14,
        "text": "Matrix"
      }
    ],
    "occlude": [
      {
        "x": 0.52,
        "y": 0.49,
        "w": 0.12,
        "h": 0.15,
        "text": "Hide label"
      }
    ]
  },
  "dysplasia_vs_normal_epithelium.png": {
    "eli5": "Dysplasia: disordered maturation, nuclear atypia; compare to normal epithelium.",
    "labels": [
      {
        "x": 0.72,
        "y": 0.7,
        "w": 0.17,
        "h": 0.16,
        "text": "Disordered maturation"
      },
      {
        "x": 0.57,
        "y": 0.42,
        "w": 0.19,
        "h": 0.14,
        "text": "Nuclear atypia"
      }
    ],
    "occlude": [
      {
        "x": 0.61,
        "y": 0.5,
        "w": 0.12,
        "h": 0.12,
        "text": "Hide label"
      }
    ]
  },
  "epithelial_tissue_gi_lining.png": {
    "eli5": "GI epithelium with goblet cells; crypts/villi vary by segment.",
    "labels": [
      {
        "x": 0.4,
        "y": 0.72,
        "w": 0.13,
        "h": 0.08,
        "text": "Crypt/Villus"
      },
      {
        "x": 0.3,
        "y": 0.49,
        "w": 0.17,
        "h": 0.13,
        "text": "Goblet cells"
      }
    ],
    "occlude": [
      {
        "x": 0.47,
        "y": 0.15,
        "w": 0.15,
        "h": 0.13,
        "text": "Hide label"
      }
    ]
  },
  "elastic_lamina_black.png": {
    "eli5": "Elastic stain highlighting wavy black elastic laminae in medium arteries.",
    "labels": [
      {
        "x": 0.42,
        "y": 0.6,
        "w": 0.14,
        "h": 0.17,
        "text": "Elastic lamina"
      },
      {
        "x": 0.71,
        "y": 0.63,
        "w": 0.14,
        "h": 0.15,
        "text": "Elastic fibers"
      }
    ],
    "occlude": [
      {
        "x": 0.14,
        "y": 0.44,
        "w": 0.22,
        "h": 0.09,
        "text": "Hide label"
      }
    ]
  },
  "giemsa_stain_parasite.png": {
    "eli5": "Giemsa: intracellular parasite with blue cytoplasm and red chromatin dot.",
    "labels": [
      {
        "x": 0.32,
        "y": 0.28,
        "w": 0.19,
        "h": 0.15,
        "text": "Parasite in RBC"
      },
      {
        "x": 0.56,
        "y": 0.53,
        "w": 0.19,
        "h": 0.13,
        "text": "Chromatin dot"
      }
    ],
    "occlude": [
      {
        "x": 0.28,
        "y": 0.47,
        "w": 0.12,
        "h": 0.17,
        "text": "Hide label"
      }
    ]
  },
  "gram_stain_bacteria.png": {
    "eli5": "Gram stain: Gram+ purple, Gram\u2212 pink; mix of cocci/bacilli.",
    "labels": [
      {
        "x": 0.35,
        "y": 0.61,
        "w": 0.16,
        "h": 0.18,
        "text": "Gram-positive (purple)"
      },
      {
        "x": 0.46,
        "y": 0.32,
        "w": 0.19,
        "h": 0.18,
        "text": "Gram-negative (pink)"
      }
    ],
    "occlude": [
      {
        "x": 0.73,
        "y": 0.3,
        "w": 0.14,
        "h": 0.15,
        "text": "Hide label"
      }
    ]
  },
  "hyperchromasia_vs_normal.png": {
    "eli5": "Hyperchromasia: darker, denser nuclei vs normal chromatin.",
    "labels": [
      {
        "x": 0.32,
        "y": 0.26,
        "w": 0.17,
        "h": 0.17,
        "text": "Hyperchromatic nuclei"
      },
      {
        "x": 0.32,
        "y": 0.2,
        "w": 0.12,
        "h": 0.09,
        "text": "Normal nuclei"
      }
    ],
    "occlude": [
      {
        "x": 0.47,
        "y": 0.36,
        "w": 0.19,
        "h": 0.13,
        "text": "Hide label"
      }
    ]
  },
  "immunofluorescence_direct_indirect.png": {
    "eli5": "Direct vs indirect IF: fluorophore on primary vs on secondary antibody.",
    "labels": [
      {
        "x": 0.15,
        "y": 0.3,
        "w": 0.13,
        "h": 0.18,
        "text": "Direct IF"
      },
      {
        "x": 0.33,
        "y": 0.22,
        "w": 0.17,
        "h": 0.09,
        "text": "Indirect IF"
      }
    ],
    "occlude": [
      {
        "x": 0.46,
        "y": 0.44,
        "w": 0.11,
        "h": 0.09,
        "text": "Hide label"
      }
    ]
  },
  "immunohistochemistry_schematic.png": {
    "eli5": "Indirect IHC: primary binds antigen; enzyme-labeled secondary makes color product.",
    "labels": [
      {
        "x": 0.25,
        "y": 0.64,
        "w": 0.17,
        "h": 0.13,
        "text": "Primary antibody"
      },
      {
        "x": 0.73,
        "y": 0.51,
        "w": 0.14,
        "h": 0.15,
        "text": "Enzyme-linked secondary"
      }
    ],
    "occlude": [
      {
        "x": 0.71,
        "y": 0.69,
        "w": 0.13,
        "h": 0.09,
        "text": "Hide label"
      }
    ]
  },
  "last_two_tier_system_lsil_hsil.png": {
    "eli5": "Two-tier system: LSIL vs HSIL for squamous intraepithelial lesions.",
    "labels": [
      {
        "x": 0.15,
        "y": 0.18,
        "w": 0.2,
        "h": 0.12,
        "text": "LSIL"
      },
      {
        "x": 0.65,
        "y": 0.6,
        "w": 0.2,
        "h": 0.12,
        "text": "HSIL"
      }
    ],
    "occlude": [
      {
        "x": 0.02,
        "y": 0.02,
        "w": 0.3,
        "h": 0.1,
        "text": "title_top_left"
      },
      {
        "x": 0.68,
        "y": 0.02,
        "w": 0.3,
        "h": 0.1,
        "text": "title_top_right"
      },
      {
        "x": 0.02,
        "y": 0.88,
        "w": 0.3,
        "h": 0.1,
        "text": "title_bottom_left"
      },
      {
        "x": 0.68,
        "y": 0.88,
        "w": 0.3,
        "h": 0.1,
        "text": "title_bottom_right"
      }
    ]
  },
  "leep_procedure_diagram.png": {
    "eli5": "LEEP removes cervical transformation zone using a loop electrode.",
    "labels": [
      {
        "x": 0.15,
        "y": 0.18,
        "w": 0.2,
        "h": 0.12,
        "text": "Transformation zone"
      },
      {
        "x": 0.65,
        "y": 0.6,
        "w": 0.2,
        "h": 0.12,
        "text": "LSIL/HSIL region"
      }
    ],
    "occlude": [
      {
        "x": 0.02,
        "y": 0.02,
        "w": 0.3,
        "h": 0.1,
        "text": "title_top_left"
      },
      {
        "x": 0.68,
        "y": 0.02,
        "w": 0.3,
        "h": 0.1,
        "text": "title_top_right"
      },
      {
        "x": 0.02,
        "y": 0.88,
        "w": 0.3,
        "h": 0.1,
        "text": "title_bottom_left"
      },
      {
        "x": 0.68,
        "y": 0.88,
        "w": 0.3,
        "h": 0.1,
        "text": "title_bottom_right"
      }
    ]
  },
  "melanocytes_skin_he.png": {
    "eli5": "Melanocytes in epidermis produce melanin; look for dendritic processes.",
    "labels": [
      {
        "x": 0.15,
        "y": 0.18,
        "w": 0.2,
        "h": 0.12,
        "text": "Melanocytes"
      },
      {
        "x": 0.65,
        "y": 0.6,
        "w": 0.2,
        "h": 0.12,
        "text": "Keratinocytes"
      }
    ],
    "occlude": [
      {
        "x": 0.02,
        "y": 0.02,
        "w": 0.3,
        "h": 0.1,
        "text": "title_top_left"
      },
      {
        "x": 0.68,
        "y": 0.02,
        "w": 0.3,
        "h": 0.1,
        "text": "title_top_right"
      },
      {
        "x": 0.02,
        "y": 0.88,
        "w": 0.3,
        "h": 0.1,
        "text": "title_bottom_left"
      },
      {
        "x": 0.68,
        "y": 0.88,
        "w": 0.3,
        "h": 0.1,
        "text": "title_bottom_right"
      }
    ]
  },
  "mucicarmine_stain_mucins.png": {
    "eli5": "Mucicarmine stains epithelial mucin deep rose; useful in mucinous tumors.",
    "labels": [
      {
        "x": 0.15,
        "y": 0.18,
        "w": 0.2,
        "h": 0.12,
        "text": "Mucin (rose)"
      },
      {
        "x": 0.65,
        "y": 0.6,
        "w": 0.2,
        "h": 0.12,
        "text": "Background"
      }
    ],
    "occlude": [
      {
        "x": 0.02,
        "y": 0.02,
        "w": 0.3,
        "h": 0.1,
        "text": "title_top_left"
      },
      {
        "x": 0.68,
        "y": 0.02,
        "w": 0.3,
        "h": 0.1,
        "text": "title_top_right"
      },
      {
        "x": 0.02,
        "y": 0.88,
        "w": 0.3,
        "h": 0.1,
        "text": "title_bottom_left"
      },
      {
        "x": 0.68,
        "y": 0.88,
        "w": 0.3,
        "h": 0.1,
        "text": "title_bottom_right"
      }
    ]
  },
  "nervous_tissue_brain.png": {
    "eli5": "Neurons with cell bodies and glia; identify neuropil and nuclei.",
    "labels": [
      {
        "x": 0.15,
        "y": 0.18,
        "w": 0.2,
        "h": 0.12,
        "text": "Neuron soma"
      },
      {
        "x": 0.65,
        "y": 0.6,
        "w": 0.2,
        "h": 0.12,
        "text": "Glial cells"
      }
    ],
    "occlude": [
      {
        "x": 0.02,
        "y": 0.02,
        "w": 0.3,
        "h": 0.1,
        "text": "title_top_left"
      },
      {
        "x": 0.68,
        "y": 0.02,
        "w": 0.3,
        "h": 0.1,
        "text": "title_top_right"
      },
      {
        "x": 0.02,
        "y": 0.88,
        "w": 0.3,
        "h": 0.1,
        "text": "title_bottom_left"
      },
      {
        "x": 0.68,
        "y": 0.88,
        "w": 0.3,
        "h": 0.1,
        "text": "title_bottom_right"
      }
    ]
  },
  "nuclear_changes_euchromatin_heterochromatin.png": {
    "eli5": "Euchromatin is lighter/active; heterochromatin is darker/inactive.",
    "labels": [
      {
        "x": 0.15,
        "y": 0.18,
        "w": 0.2,
        "h": 0.12,
        "text": "Euchromatin"
      },
      {
        "x": 0.65,
        "y": 0.6,
        "w": 0.2,
        "h": 0.12,
        "text": "Heterochromatin"
      }
    ],
    "occlude": [
      {
        "x": 0.02,
        "y": 0.02,
        "w": 0.3,
        "h": 0.1,
        "text": "title_top_left"
      },
      {
        "x": 0.68,
        "y": 0.02,
        "w": 0.3,
        "h": 0.1,
        "text": "title_top_right"
      },
      {
        "x": 0.02,
        "y": 0.88,
        "w": 0.3,
        "h": 0.1,
        "text": "title_bottom_left"
      },
      {
        "x": 0.68,
        "y": 0.88,
        "w": 0.3,
        "h": 0.1,
        "text": "title_bottom_right"
      }
    ]
  },
  "pas_diastase_removed_glycogen.png": {
    "eli5": "PAS-D: removes glycogen; residual PAS positivity indicates glycoproteins.",
    "labels": [
      {
        "x": 0.15,
        "y": 0.18,
        "w": 0.2,
        "h": 0.12,
        "text": "Glycogen removed"
      },
      {
        "x": 0.65,
        "y": 0.6,
        "w": 0.2,
        "h": 0.12,
        "text": "PAS+ glycoproteins"
      }
    ],
    "occlude": [
      {
        "x": 0.02,
        "y": 0.02,
        "w": 0.3,
        "h": 0.1,
        "text": "title_top_left"
      },
      {
        "x": 0.68,
        "y": 0.02,
        "w": 0.3,
        "h": 0.1,
        "text": "title_top_right"
      },
      {
        "x": 0.02,
        "y": 0.88,
        "w": 0.3,
        "h": 0.1,
        "text": "title_bottom_left"
      },
      {
        "x": 0.68,
        "y": 0.88,
        "w": 0.3,
        "h": 0.1,
        "text": "title_bottom_right"
      }
    ]
  },
  "pas_magenta_glycoproteins.png": {
    "eli5": "PAS stains glycogen and glycoproteins magenta.",
    "labels": [
      {
        "x": 0.15,
        "y": 0.18,
        "w": 0.2,
        "h": 0.12,
        "text": "PAS+ material"
      },
      {
        "x": 0.65,
        "y": 0.6,
        "w": 0.2,
        "h": 0.12,
        "text": "Nuclei"
      }
    ],
    "occlude": [
      {
        "x": 0.02,
        "y": 0.02,
        "w": 0.3,
        "h": 0.1,
        "text": "title_top_left"
      },
      {
        "x": 0.68,
        "y": 0.02,
        "w": 0.3,
        "h": 0.1,
        "text": "title_top_right"
      },
      {
        "x": 0.02,
        "y": 0.88,
        "w": 0.3,
        "h": 0.1,
        "text": "title_bottom_left"
      },
      {
        "x": 0.68,
        "y": 0.88,
        "w": 0.3,
        "h": 0.1,
        "text": "title_bottom_right"
      }
    ]
  },
  "perls_prussian_blue_iron.png": {
    "eli5": "Perls' Prussian blue highlights iron deposits (hemosiderin) in blue.",
    "labels": [
      {
        "x": 0.15,
        "y": 0.18,
        "w": 0.2,
        "h": 0.12,
        "text": "Iron (blue)"
      },
      {
        "x": 0.65,
        "y": 0.6,
        "w": 0.2,
        "h": 0.12,
        "text": "Parenchyma"
      }
    ],
    "occlude": [
      {
        "x": 0.02,
        "y": 0.02,
        "w": 0.3,
        "h": 0.1,
        "text": "title_top_left"
      },
      {
        "x": 0.68,
        "y": 0.02,
        "w": 0.3,
        "h": 0.1,
        "text": "title_top_right"
      },
      {
        "x": 0.02,
        "y": 0.88,
        "w": 0.3,
        "h": 0.1,
        "text": "title_bottom_left"
      },
      {
        "x": 0.68,
        "y": 0.88,
        "w": 0.3,
        "h": 0.1,
        "text": "title_bottom_right"
      }
    ]
  },
  "planes_of_section_diagram.png": {
    "eli5": "Planes of section: transverse, sagittal, coronal\u2014affect appearance of structures.",
    "labels": [
      {
        "x": 0.15,
        "y": 0.18,
        "w": 0.2,
        "h": 0.12,
        "text": "Transverse"
      },
      {
        "x": 0.65,
        "y": 0.6,
        "w": 0.2,
        "h": 0.12,
        "text": "Sagittal"
      }
    ],
    "occlude": [
      {
        "x": 0.02,
        "y": 0.02,
        "w": 0.3,
        "h": 0.1,
        "text": "title_top_left"
      },
      {
        "x": 0.68,
        "y": 0.02,
        "w": 0.3,
        "h": 0.1,
        "text": "title_top_right"
      },
      {
        "x": 0.02,
        "y": 0.88,
        "w": 0.3,
        "h": 0.1,
        "text": "title_bottom_left"
      },
      {
        "x": 0.68,
        "y": 0.88,
        "w": 0.3,
        "h": 0.1,
        "text": "title_bottom_right"
      }
    ]
  },
  "proscia_viewer_ui_annotations.png": {
    "eli5": "Whole-slide viewer UI showing annotation tools.",
    "labels": [
      {
        "x": 0.26,
        "y": 0.58,
        "w": 0.17,
        "h": 0.13,
        "text": "Annotation tools"
      },
      {
        "x": 0.58,
        "y": 0.69,
        "w": 0.22,
        "h": 0.1,
        "text": "Slide overview"
      }
    ],
    "occlude": [
      {
        "x": 0.71,
        "y": 0.22,
        "w": 0.17,
        "h": 0.14,
        "text": "Hide label"
      }
    ]
  },
  "reticulin_fibers_black.png": {
    "eli5": "Reticulin stain outlines delicate reticular fibers as a black network.",
    "labels": [
      {
        "x": 0.43,
        "y": 0.64,
        "w": 0.14,
        "h": 0.17,
        "text": "Reticulin fibers"
      },
      {
        "x": 0.46,
        "y": 0.36,
        "w": 0.21,
        "h": 0.17,
        "text": "Background parenchyma"
      }
    ],
    "occlude": [
      {
        "x": 0.32,
        "y": 0.3,
        "w": 0.17,
        "h": 0.09,
        "text": "Hide label"
      }
    ]
  },
  "scanning_electron_microscopy_ant.png": {
    "eli5": "SEM example; appreciate 3D surface topography.",
    "labels": [
      {
        "x": 0.68,
        "y": 0.63,
        "w": 0.11,
        "h": 0.13,
        "text": "Surface detail"
      },
      {
        "x": 0.24,
        "y": 0.13,
        "w": 0.11,
        "h": 0.12,
        "text": "Antennae"
      }
    ],
    "occlude": [
      {
        "x": 0.2,
        "y": 0.2,
        "w": 0.13,
        "h": 0.08,
        "text": "Hide label"
      }
    ]
  },
  "signs_of_malignancy_progression.png": {
    "eli5": "Progression: hyperplasia \u2192 dysplasia \u2192 carcinoma in situ \u2192 invasive cancer.",
    "labels": [
      {
        "x": 0.25,
        "y": 0.55,
        "w": 0.17,
        "h": 0.09,
        "text": "Hyperplasia \u2192 Dysplasia"
      },
      {
        "x": 0.74,
        "y": 0.6,
        "w": 0.17,
        "h": 0.16,
        "text": "CIS \u2192 Invasive"
      }
    ],
    "occlude": [
      {
        "x": 0.71,
        "y": 0.15,
        "w": 0.11,
        "h": 0.17,
        "text": "Hide label"
      }
    ]
  },
  "silver_stain_fungus.png": {
    "eli5": "GMS silver stain: fungal hyphae/yeasts appear black on pale green.",
    "labels": [
      {
        "x": 0.32,
        "y": 0.13,
        "w": 0.19,
        "h": 0.12,
        "text": "Fungal elements"
      },
      {
        "x": 0.23,
        "y": 0.22,
        "w": 0.19,
        "h": 0.12,
        "text": "Background"
      }
    ],
    "occlude": [
      {
        "x": 0.59,
        "y": 0.38,
        "w": 0.12,
        "h": 0.14,
        "text": "Hide label"
      }
    ]
  },
  "skeletal_muscle_striated.png": {
    "eli5": "Skeletal muscle: long cylindrical fibers, peripheral nuclei, cross striations.",
    "labels": [
      {
        "x": 0.47,
        "y": 0.66,
        "w": 0.21,
        "h": 0.08,
        "text": "Striations"
      },
      {
        "x": 0.09,
        "y": 0.68,
        "w": 0.19,
        "h": 0.15,
        "text": "Peripheral nuclei"
      }
    ],
    "occlude": [
      {
        "x": 0.41,
        "y": 0.22,
        "w": 0.11,
        "h": 0.17,
        "text": "Hide label"
      }
    ]
  },
  "transmission_electron_microscopy_mitochondrion.png": {
    "eli5": "TEM mitochondrion with cristae; double membrane and dense matrix.",
    "labels": [
      {
        "x": 0.4,
        "y": 0.7,
        "w": 0.11,
        "h": 0.18,
        "text": "Cristae"
      },
      {
        "x": 0.32,
        "y": 0.54,
        "w": 0.16,
        "h": 0.1,
        "text": "Double membrane"
      }
    ],
    "occlude": [
      {
        "x": 0.71,
        "y": 0.4,
        "w": 0.19,
        "h": 0.16,
        "text": "Hide label"
      }
    ]
  },
  "trichrome_collagen_blue.png": {
    "eli5": "Masson trichrome: collagen stains blue/green, muscle red, nuclei black.",
    "labels": [
      {
        "x": 0.53,
        "y": 0.55,
        "w": 0.17,
        "h": 0.14,
        "text": "Collagen (blue)"
      },
      {
        "x": 0.27,
        "y": 0.08,
        "w": 0.2,
        "h": 0.11,
        "text": "Muscle (red)"
      }
    ],
    "occlude": [
      {
        "x": 0.69,
        "y": 0.08,
        "w": 0.2,
        "h": 0.14,
        "text": "Hide label"
      }
    ]
  },
  "von_kossa_calcium_black.png": {
    "eli5": "Von Kossa highlights calcium phosphate as black deposits.",
    "labels": [
      {
        "x": 0.5,
        "y": 0.45,
        "w": 0.1,
        "h": 0.13,
        "text": "Calcium deposits"
      },
      {
        "x": 0.27,
        "y": 0.46,
        "w": 0.2,
        "h": 0.08,
        "text": "Background"
      }
    ],
    "occlude": [
      {
        "x": 0.53,
        "y": 0.08,
        "w": 0.2,
        "h": 0.16,
        "text": "Hide label"
      }
    ]
  }
}